LICENSE
README.md
pyproject.toml
setup.cfg
setup.py
pigeonking/__init__.py
pigeonking.egg-info/PKG-INFO
pigeonking.egg-info/SOURCES.txt
pigeonking.egg-info/dependency_links.txt
pigeonking.egg-info/entry_points.txt
pigeonking.egg-info/requires.txt
pigeonking.egg-info/top_level.txt