Metadata-Version: 2.1
Name: pigeonking
Version: 0.0.2
Summary: King of Pigeon
Home-page: https://github.com/yuezih/King-of-Pigeon
Author: pigeonking
Author-email: yuezih@std.uestc.edu.cn
License: UNKNOWN
Platform: UNKNOWN
License-File: LICENSE
